cs_nds/__init__.py
cs_nds/bintree.py
cs_nds/dynarray.py
cs_nds/queue.py
cs_nds/stack.py
cs_nds-0.3.1.dist-info/LICENSE
cs_nds-0.3.1.dist-info/METADATA
cs_nds-0.3.1.dist-info/WHEEL
cs_nds-0.3.1.dist-info/top_level.txt
cs_nds-0.3.1.dist-info/RECORD
