Metadata-Version: 2.1
Name: cs-nds
Version: 0.3.1
Summary: Often used things for Computer Science classes
Home-page: https://github.com/alexcoder04/cs_nds
Author: alexcoder04
Author-email: alexcoder04@protonmail.com
Classifier: Intended Audience :: Education
Classifier: License :: OSI Approved :: GNU General Public License v3 (GPLv3)
Classifier: Programming Language :: Python
Classifier: Programming Language :: Python :: 3
Classifier: Programming Language :: Python :: 3.8
Classifier: Programming Language :: Python :: 3.9
Classifier: Programming Language :: Python :: 3.10
Classifier: Operating System :: OS Independent
License-File: LICENSE
